Metadata-Version: 2.1
Name: bigartm10
Version: 0.10.1
Summary: BigARTM: the state-of-the-art platform for topic modeling
Home-page: https://github.com/bigartm/bigartm
Maintainer: ARTM developers group
Maintainer-email: artm_dev+pypi_develop@googlegroups.com
License: New BSD license
Platform: UNKNOWN
Classifier: Development Status :: 4 - Beta
Classifier: Intended Audience :: Developers
Classifier: Intended Audience :: Science/Research
Classifier: License :: OSI Approved
Classifier: Operating System :: POSIX
Classifier: Operating System :: Unix
Classifier: Programming Language :: Python
Classifier: Programming Language :: Python :: 2
Classifier: Programming Language :: Python :: 2.7
Classifier: Programming Language :: Python :: 3
Classifier: Programming Language :: Python :: 3.4
Classifier: Programming Language :: Python :: 3.5
Classifier: Programming Language :: Python :: 3.6
Classifier: Programming Language :: Python :: 3.7
Classifier: Programming Language :: Python :: 3.8
Classifier: Topic :: Scientific/Engineering
Classifier: Topic :: Scientific/Engineering :: Information Analysis
Classifier: Topic :: Software Development
Requires-Dist: pandas
Requires-Dist: numpy
Requires-Dist: packaging
Requires-Dist: tqdm
Requires-Dist: protobuf (>=3.0)
